badwing/__init__.py
badwing/__main__.py
badwing/app.py
badwing/assets.py
badwing/avatar.py
badwing/background.py
badwing/ball.py
badwing/barrier.py
badwing/box.py
badwing/brain.py
badwing/character.py
badwing/coin.py
badwing/constants.py
badwing/controller.py
badwing/debug.py
badwing/dialog.py
badwing/dude.py
badwing/effect.py
badwing/emitter.py
badwing/firework.py
badwing/flag.py
badwing/geom.py
badwing/ladder.py
badwing/layer.py
badwing/level.py
badwing/main.py
badwing/model.py
badwing/obstacle.py
badwing/particle.py
badwing/player.py
badwing/scene.py
badwing/screen.py
badwing/skateboard.py
badwing/tile.py
badwing/version.py
badwing/view.py
badwing/butterfly/__init__.py
badwing/butterfly/brain.py
badwing/character/__init__.py
badwing/character/character.py
badwing/character/kinematic.py
badwing/character/layer.py
badwing/character/sprite.py
badwing/character/controller/__init__.py
badwing/character/controller/controller.py
badwing/character/controller/kinematic.py
badwing/characters/__init__.py
badwing/characters/blob.py
badwing/characters/factory.py
badwing/characters/pc.py
badwing/characters/skateboard.py
badwing/characters/butterfly/__init__.py
badwing/characters/butterfly/brain.py
badwing/characters/butterfly/butterfly.py
badwing/characters/butterfly/sprite.py
badwing/characters/robot/__init__.py
badwing/characters/robot/brain.py
badwing/characters/robot/robot.py
badwing/characters/skeleton/__init__.py
badwing/characters/skeleton/brain.py
badwing/characters/skeleton/skeleton.py
badwing/command/__init__.py
badwing/commands/__init__.py
badwing/dialogs/beatlevel.py
badwing/dialogs/pause.py
badwing/level/__init__.py
badwing/level/level.py
badwing/level/sticker.py
badwing/level/tile.py
badwing/levels/end.py
badwing/levels/level1.py
badwing/levels/level2.py
badwing/levels/start.py
badwing/physics/__init__.py
badwing/physics/dynamic.py
badwing/physics/engine.py
badwing/physics/kinematic.py
badwing/physics/physics.py
badwing/physics/static.py
badwing/physics/util.py
badwing-0.1.dev67.dist-info/LICENSE
badwing-0.1.dev67.dist-info/METADATA
badwing-0.1.dev67.dist-info/WHEEL
badwing-0.1.dev67.dist-info/entry_points.txt
badwing-0.1.dev67.dist-info/top_level.txt
badwing-0.1.dev67.dist-info/RECORD
