Metadata-Version: 2.1
Name: badwing
Version: 0.1.dev67
Summary: Skateboarder/Platformer/Lepidopterist Game using Arcade & Pymunk
Home-page: https://github.com/kfields/badwing
Author: Kurtis Fields
Author-email: kurtisfields@gmail.com
License: UNKNOWN
Platform: UNKNOWN
Classifier: Programming Language :: Python :: 3
Classifier: License :: OSI Approved :: MIT License
Classifier: Operating System :: OS Independent
Requires-Python: >=3.6
Requires-Dist: PyGLM (==1.1.8)
Requires-Dist: arcade (==2.4.1)
Requires-Dist: click (==7.1.1)
Requires-Dist: pymunk (==5.6.0)
